{
"meta":{"test_sets":[],"test_metrics":[],"learn_metrics":[{"best_value":"Min","name":"RMSE"}],"launch_mode":"Train","parameters":"","iteration_count":400,"learn_sets":["learn"],"name":"experiment"},
"iterations":[
{"learn":[0.8406369783],"iteration":0,"passed_time":0.06570186133,"remaining_time":26.21504267},
{"learn":[0.8346980103],"iteration":1,"passed_time":0.1274054876,"remaining_time":25.35369203},
{"learn":[0.8286744339],"iteration":2,"passed_time":0.1957191678,"remaining_time":25.90016987},
{"learn":[0.8230089127],"iteration":3,"passed_time":0.2596687109,"remaining_time":25.70720238},
{"learn":[0.817397598],"iteration":4,"passed_time":0.322396086,"remaining_time":25.4692908},
{"learn":[0.8119714112],"iteration":5,"passed_time":0.3858595006,"remaining_time":25.3381072},
{"learn":[0.806519011],"iteration":6,"passed_time":0.4433671778,"remaining_time":24.89190012},
{"learn":[0.8012678977],"iteration":7,"passed_time":0.5034554103,"remaining_time":24.66931511},
{"learn":[0.7962730083],"iteration":8,"passed_time":0.5666203789,"remaining_time":24.61650757},
{"learn":[0.7914107601],"iteration":9,"passed_time":0.6272452182,"remaining_time":24.46256351},
{"learn":[0.7868411123],"iteration":10,"passed_time":0.7021340697,"remaining_time":24.83001392},
{"learn":[0.7822978195],"iteration":11,"passed_time":0.7725156259,"remaining_time":24.97800524},
{"learn":[0.77804165],"iteration":12,"passed_time":0.8409267484,"remaining_time":25.03374243},
{"learn":[0.7737444762],"iteration":13,"passed_time":0.9020301059,"remaining_time":24.87025863},
{"learn":[0.7700032442],"iteration":14,"passed_time":0.9407733014,"remaining_time":24.14651474},
{"learn":[0.766044563],"iteration":15,"passed_time":0.9987809481,"remaining_time":23.97074276},
{"learn":[0.7621454686],"iteration":16,"passed_time":1.057843828,"remaining_time":23.83259918},
{"learn":[0.7583939589],"iteration":17,"passed_time":1.124449994,"remaining_time":23.86332764},
{"learn":[0.754888636],"iteration":18,"passed_time":1.1914855,"remaining_time":23.89241976},
{"learn":[0.7513307859],"iteration":19,"passed_time":1.254392381,"remaining_time":23.83345525},
{"learn":[0.7479905325],"iteration":20,"passed_time":1.319946797,"remaining_time":23.82189696},
{"learn":[0.7447489407],"iteration":21,"passed_time":1.384308834,"remaining_time":23.78494269},
{"learn":[0.7415851612],"iteration":22,"passed_time":1.44368326,"remaining_time":23.6638517},
{"learn":[0.7385550811],"iteration":23,"passed_time":1.503235546,"remaining_time":23.55069022},
{"learn":[0.7355810686],"iteration":24,"passed_time":1.571899516,"remaining_time":23.57849275},
{"learn":[0.732669542],"iteration":25,"passed_time":1.632945781,"remaining_time":23.48929701},
{"learn":[0.7299788345],"iteration":26,"passed_time":1.696066266,"remaining_time":23.43084138},
{"learn":[0.7272479275],"iteration":27,"passed_time":1.755910363,"remaining_time":23.32852339},
{"learn":[0.724588136],"iteration":28,"passed_time":1.821760993,"remaining_time":23.30597685},
{"learn":[0.7221197238],"iteration":29,"passed_time":1.888817099,"remaining_time":23.29541089},
{"learn":[0.7196238703],"iteration":30,"passed_time":1.956065548,"remaining_time":23.28348992},
{"learn":[0.7173414911],"iteration":31,"passed_time":2.021855886,"remaining_time":23.25134269},
{"learn":[0.7151489268],"iteration":32,"passed_time":2.092879205,"remaining_time":23.27535359},
{"learn":[0.7129736941],"iteration":33,"passed_time":2.156375024,"remaining_time":23.21274291},
{"learn":[0.7109104151],"iteration":34,"passed_time":2.218325365,"remaining_time":23.13396452},
{"learn":[0.7087411355],"iteration":35,"passed_time":2.28070349,"remaining_time":23.0604464},
{"learn":[0.7068172218],"iteration":36,"passed_time":2.331510148,"remaining_time":22.87400497},
{"learn":[0.7048509928],"iteration":37,"passed_time":2.389087055,"remaining_time":22.75919774},
{"learn":[0.7029204155],"iteration":38,"passed_time":2.453899381,"remaining_time":22.7142994},
{"learn":[0.7011974195],"iteration":39,"passed_time":2.515841617,"remaining_time":22.64257455},
{"learn":[0.6995265795],"iteration":40,"passed_time":2.579757016,"remaining_time":22.58860412},
{"learn":[0.6978510148],"iteration":41,"passed_time":2.643389333,"remaining_time":22.53174717},
{"learn":[0.6962139336],"iteration":42,"passed_time":2.701714211,"remaining_time":22.43051101},
{"learn":[0.6947262888],"iteration":43,"passed_time":2.775985181,"remaining_time":22.46024374},
{"learn":[0.693255114],"iteration":44,"passed_time":2.836100763,"remaining_time":22.3736838},
{"learn":[0.6919210955],"iteration":45,"passed_time":2.907318296,"remaining_time":22.37371037},
{"learn":[0.6906241306],"iteration":46,"passed_time":2.946334579,"remaining_time":22.12885332},
{"learn":[0.6893078488],"iteration":47,"passed_time":3.005787957,"remaining_time":22.04244502},
{"learn":[0.687979073],"iteration":48,"passed_time":3.075528306,"remaining_time":22.03082521},
{"learn":[0.686664645],"iteration":49,"passed_time":3.146824713,"remaining_time":22.02777299},
{"learn":[0.6854104277],"iteration":50,"passed_time":3.209706995,"remaining_time":21.96446551},
{"learn":[0.6842354984],"iteration":51,"passed_time":3.271555885,"remaining_time":21.89425861},
{"learn":[0.6831322786],"iteration":52,"passed_time":3.332261038,"remaining_time":21.81687887},
{"learn":[0.6819867811],"iteration":53,"passed_time":3.396976513,"remaining_time":21.76581247},
{"learn":[0.6808561313],"iteration":54,"passed_time":3.467283985,"remaining_time":21.74932681},
{"learn":[0.6798141998],"iteration":55,"passed_time":3.52758027,"remaining_time":21.66942166},
{"learn":[0.6788724263],"iteration":56,"passed_time":3.592024306,"remaining_time":21.61516381},
{"learn":[0.6778590908],"iteration":57,"passed_time":3.655761762,"remaining_time":21.55638832},
{"learn":[0.6769421728],"iteration":58,"passed_time":3.720555158,"remaining_time":21.50354761},
{"learn":[0.6760304793],"iteration":59,"passed_time":3.780348681,"remaining_time":21.42197586},
{"learn":[0.6752054909],"iteration":60,"passed_time":3.843033258,"remaining_time":21.35718483},
{"learn":[0.6743867227],"iteration":61,"passed_time":3.912964098,"remaining_time":21.33196557},
{"learn":[0.6735408574],"iteration":62,"passed_time":3.976573167,"remaining_time":21.27151043},
{"learn":[0.6728103756],"iteration":63,"passed_time":4.043008146,"remaining_time":21.22579277},
{"learn":[0.6720596297],"iteration":64,"passed_time":4.112366276,"remaining_time":21.19450312},
{"learn":[0.671335375],"iteration":65,"passed_time":4.177589219,"remaining_time":21.14113332},
{"learn":[0.6706316249],"iteration":66,"passed_time":4.244795308,"remaining_time":21.09726623},
{"learn":[0.6699674347],"iteration":67,"passed_time":4.304956781,"remaining_time":21.0183184},
{"learn":[0.6693258953],"iteration":68,"passed_time":4.372298752,"remaining_time":20.97436068},
{"learn":[0.6687088562],"iteration":69,"passed_time":4.436125403,"remaining_time":20.91316261},
{"learn":[0.6681101436],"iteration":70,"passed_time":4.501020033,"remaining_time":20.85683931},
{"learn":[0.6675002303],"iteration":71,"passed_time":4.56051807,"remaining_time":20.77569343},
{"learn":[0.6668819475],"iteration":72,"passed_time":4.628010269,"remaining_time":20.73095011},
{"learn":[0.6663809698],"iteration":73,"passed_time":4.685856172,"remaining_time":20.64309611},
{"learn":[0.6658250295],"iteration":74,"passed_time":4.750789005,"remaining_time":20.58675236},
{"learn":[0.665285088],"iteration":75,"passed_time":4.806087404,"remaining_time":20.48910946},
{"learn":[0.6647924357],"iteration":76,"passed_time":4.874219147,"remaining_time":20.4463998},
{"learn":[0.664341571],"iteration":77,"passed_time":4.939981607,"remaining_time":20.3932574},
{"learn":[0.6638524989],"iteration":78,"passed_time":5.002667279,"remaining_time":20.32729363},
{"learn":[0.6634154523],"iteration":79,"passed_time":5.05968726,"remaining_time":20.23874904},
{"learn":[0.6629340458],"iteration":80,"passed_time":5.124125593,"remaining_time":20.18019832},
{"learn":[0.6625342905],"iteration":81,"passed_time":5.186584935,"remaining_time":20.11382938},
{"learn":[0.6621335906],"iteration":82,"passed_time":5.243452031,"remaining_time":20.02619631},
{"learn":[0.6617306749],"iteration":83,"passed_time":5.303842462,"remaining_time":19.95255021},
{"learn":[0.6613020563],"iteration":84,"passed_time":5.370968585,"remaining_time":19.9041777},
{"learn":[0.6609407876],"iteration":85,"passed_time":5.43393075,"remaining_time":19.84016576},
{"learn":[0.6605624119],"iteration":86,"passed_time":5.497405333,"remaining_time":19.77802148},
{"learn":[0.6602468906],"iteration":87,"passed_time":5.546392168,"remaining_time":19.66448132},
{"learn":[0.6599287144],"iteration":88,"passed_time":5.612396791,"remaining_time":19.61185845},
{"learn":[0.6595769309],"iteration":89,"passed_time":5.677362849,"remaining_time":19.55536092},
{"learn":[0.6592733429],"iteration":90,"passed_time":5.742643896,"remaining_time":19.49974686},
{"learn":[0.658904939],"iteration":91,"passed_time":5.806782167,"remaining_time":19.44009682},
{"learn":[0.6585929646],"iteration":92,"passed_time":5.864955932,"remaining_time":19.36066098},
{"learn":[0.6583184084],"iteration":93,"passed_time":5.92651389,"remaining_time":19.29269415},
{"learn":[0.6580299725],"iteration":94,"passed_time":5.989891359,"remaining_time":19.23070384},
{"learn":[0.6577283369],"iteration":95,"passed_time":6.052310577,"remaining_time":19.16565016},
{"learn":[0.6574550536],"iteration":96,"passed_time":6.116736757,"remaining_time":19.10691997},
{"learn":[0.6571771215],"iteration":97,"passed_time":6.180632027,"remaining_time":19.04643747},
{"learn":[0.6569304657],"iteration":98,"passed_time":6.240732012,"remaining_time":18.97434682},
{"learn":[0.6566749773],"iteration":99,"passed_time":6.298499471,"remaining_time":18.89549841},
{"learn":[0.6564347764],"iteration":100,"passed_time":6.361041168,"remaining_time":18.83120108},
{"learn":[0.6562267893],"iteration":101,"passed_time":6.424239516,"remaining_time":18.76885663},
{"learn":[0.6559746354],"iteration":102,"passed_time":6.488929627,"remaining_time":18.71079708},
{"learn":[0.6557494587],"iteration":103,"passed_time":6.553751557,"remaining_time":18.6529852},
{"learn":[0.6555356337],"iteration":104,"passed_time":6.622626354,"remaining_time":18.60642642},
{"learn":[0.6552973872],"iteration":105,"passed_time":6.682400726,"remaining_time":18.53420579},
{"learn":[0.6551076351],"iteration":106,"passed_time":6.747270443,"remaining_time":18.47617046},
{"learn":[0.6549166158],"iteration":107,"passed_time":6.809058065,"remaining_time":18.40967551},
{"learn":[0.654720175],"iteration":108,"passed_time":6.868479688,"remaining_time":18.33695036},
{"learn":[0.654531314],"iteration":109,"passed_time":6.939301971,"remaining_time":18.29452338},
{"learn":[0.6543567013],"iteration":110,"passed_time":7.007661737,"remaining_time":18.24517335},
{"learn":[0.6540912197],"iteration":111,"passed_time":7.069851679,"remaining_time":18.1796186},
{"learn":[0.6538213969],"iteration":112,"passed_time":7.1309652,"remaining_time":18.11138949},
{"learn":[0.6535175132],"iteration":113,"passed_time":7.187017863,"remaining_time":18.03058867},
{"learn":[0.6532287504],"iteration":114,"passed_time":7.24794275,"remaining_time":17.9622929},
{"learn":[0.6529414784],"iteration":115,"passed_time":7.297024125,"remaining_time":17.86512803},
{"learn":[0.6526597548],"iteration":116,"passed_time":7.345188769,"remaining_time":17.76656771},
{"learn":[0.6523895138],"iteration":117,"passed_time":7.401699803,"remaining_time":17.688808},
{"learn":[0.652139394],"iteration":118,"passed_time":7.461338233,"remaining_time":17.61879028},
{"learn":[0.651906674],"iteration":119,"passed_time":7.522403213,"remaining_time":17.55227416},
{"learn":[0.651677657],"iteration":120,"passed_time":7.573843094,"remaining_time":17.46365474},
{"learn":[0.6514249397],"iteration":121,"passed_time":7.619806548,"remaining_time":17.36316574},
{"learn":[0.6512128472],"iteration":122,"passed_time":7.670913609,"remaining_time":17.27514691},
{"learn":[0.6509666053],"iteration":123,"passed_time":7.734072165,"remaining_time":17.21454772},
{"learn":[0.6507418078],"iteration":124,"passed_time":7.792738885,"remaining_time":17.14402555},
{"learn":[0.6505536055],"iteration":125,"passed_time":7.847892811,"remaining_time":17.06605262},
{"learn":[0.6503504473],"iteration":126,"passed_time":7.910943792,"remaining_time":17.00541461},
{"learn":[0.6501409901],"iteration":127,"passed_time":7.962832781,"remaining_time":16.92101966},
{"learn":[0.6499263023],"iteration":128,"passed_time":8.019734978,"remaining_time":16.8476603},
{"learn":[0.649737789],"iteration":129,"passed_time":8.067121325,"remaining_time":16.75479044},
{"learn":[0.6495696675],"iteration":130,"passed_time":8.132272189,"remaining_time":16.69909327},
{"learn":[0.6493953954],"iteration":131,"passed_time":8.190339844,"remaining_time":16.6288718},
{"learn":[0.6491955274],"iteration":132,"passed_time":8.244561306,"remaining_time":16.55111179},
{"learn":[0.6490103028],"iteration":133,"passed_time":8.303875654,"remaining_time":16.48381287},
{"learn":[0.6488548192],"iteration":134,"passed_time":8.359835559,"remaining_time":16.41004758},
{"learn":[0.6486775373],"iteration":135,"passed_time":8.442950271,"remaining_time":16.38925641},
{"learn":[0.6485230864],"iteration":136,"passed_time":8.500018979,"remaining_time":16.31755468},
{"learn":[0.6484104297],"iteration":137,"passed_time":8.533834,"remaining_time":16.20191672},
{"learn":[0.6482601671],"iteration":138,"passed_time":8.599916449,"remaining_time":16.14804456},
{"learn":[0.6481019941],"iteration":139,"passed_time":8.647747495,"remaining_time":16.06010249},
{"learn":[0.6479579187],"iteration":140,"passed_time":8.711243699,"remaining_time":16.00150438},
{"learn":[0.6478065102],"iteration":141,"passed_time":8.764338523,"remaining_time":15.92393901},
{"learn":[0.6476835028],"iteration":142,"passed_time":8.818505064,"remaining_time":15.84864197},
{"learn":[0.6475682792],"iteration":143,"passed_time":8.887244047,"remaining_time":15.79954497},
{"learn":[0.6474283951],"iteration":144,"passed_time":8.930094311,"remaining_time":15.70464862},
{"learn":[0.6473028942],"iteration":145,"passed_time":8.985783141,"remaining_time":15.63280081},
{"learn":[0.6471929266],"iteration":146,"passed_time":9.034574631,"remaining_time":15.54930192},
{"learn":[0.6470500412],"iteration":147,"passed_time":9.086454153,"remaining_time":15.47153004},
{"learn":[0.646930411],"iteration":148,"passed_time":9.146892701,"remaining_time":15.40852395},
{"learn":[0.6468133053],"iteration":149,"passed_time":9.20693754,"remaining_time":15.3448959},
{"learn":[0.6466951642],"iteration":150,"passed_time":9.255070025,"remaining_time":15.26167176},
{"learn":[0.6465912351],"iteration":151,"passed_time":9.314202943,"remaining_time":15.19685743},
{"learn":[0.646492911],"iteration":152,"passed_time":9.374264775,"remaining_time":15.13361699},
{"learn":[0.6464066581],"iteration":153,"passed_time":9.43030086,"remaining_time":15.06398709},
{"learn":[0.6463268349],"iteration":154,"passed_time":9.496685074,"remaining_time":15.01088931},
{"learn":[0.6462327138],"iteration":155,"passed_time":9.54700922,"remaining_time":14.9325016},
{"learn":[0.6461215971],"iteration":156,"passed_time":9.612006222,"remaining_time":14.87718161},
{"learn":[0.6460245641],"iteration":157,"passed_time":9.672311333,"remaining_time":14.8145528},
{"learn":[0.6459137202],"iteration":158,"passed_time":9.729874986,"remaining_time":14.74779793},
{"learn":[0.645829844],"iteration":159,"passed_time":9.788398221,"remaining_time":14.68259733},
{"learn":[0.6457212191],"iteration":160,"passed_time":9.851704653,"remaining_time":14.6245802},
{"learn":[0.6456396737],"iteration":161,"passed_time":9.912160067,"remaining_time":14.56230923},
{"learn":[0.6455394567],"iteration":162,"passed_time":9.981551527,"remaining_time":14.51305345},
{"learn":[0.6454474955],"iteration":163,"passed_time":10.03715676,"remaining_time":14.44371339},
{"learn":[0.6453614459],"iteration":164,"passed_time":10.09453533,"remaining_time":14.37706547},
{"learn":[0.6452635649],"iteration":165,"passed_time":10.15954674,"remaining_time":14.32128878},
{"learn":[0.6451927387],"iteration":166,"passed_time":10.22601064,"remaining_time":14.26742802},
{"learn":[0.6451111105],"iteration":167,"passed_time":10.29148826,"remaining_time":14.21205522},
{"learn":[0.6450200573],"iteration":168,"passed_time":10.35352174,"remaining_time":14.15185516},
{"learn":[0.6449364563],"iteration":169,"passed_time":10.41426428,"remaining_time":14.08988697},
{"learn":[0.6448471298],"iteration":170,"passed_time":10.47933683,"remaining_time":14.03373178},
{"learn":[0.6447894606],"iteration":171,"passed_time":10.52479716,"remaining_time":13.95147531},
{"learn":[0.6447166854],"iteration":172,"passed_time":10.58665016,"remaining_time":13.89115368},
{"learn":[0.6446564981],"iteration":173,"passed_time":10.65440411,"remaining_time":13.8384789},
{"learn":[0.644584863],"iteration":174,"passed_time":10.7219493,"remaining_time":13.78536338},
{"learn":[0.644505027],"iteration":175,"passed_time":10.78085876,"remaining_time":13.72109296},
{"learn":[0.6444383733],"iteration":176,"passed_time":10.83946291,"remaining_time":13.65649846},
{"learn":[0.6443757275],"iteration":177,"passed_time":10.9045968,"remaining_time":13.60011511},
{"learn":[0.6443213055],"iteration":178,"passed_time":10.96471966,"remaining_time":13.53744718},
{"learn":[0.6442249579],"iteration":179,"passed_time":11.01073554,"remaining_time":13.45756566},
{"learn":[0.6441481664],"iteration":180,"passed_time":11.06363431,"remaining_time":13.38638626},
{"learn":[0.6440792833],"iteration":181,"passed_time":11.13196222,"remaining_time":13.33388881},
{"learn":[0.6440052615],"iteration":182,"passed_time":11.19020073,"remaining_time":13.26925442},
{"learn":[0.6439422591],"iteration":183,"passed_time":11.25317939,"remaining_time":13.21025407},
{"learn":[0.6438828893],"iteration":184,"passed_time":11.30796427,"remaining_time":13.14168821},
{"learn":[0.6438199891],"iteration":185,"passed_time":11.3687129,"remaining_time":13.08013204},
{"learn":[0.6437584425],"iteration":186,"passed_time":11.42762063,"remaining_time":13.01648767},
{"learn":[0.6436941083],"iteration":187,"passed_time":11.48293458,"remaining_time":12.94884112},
{"learn":[0.6436322155],"iteration":188,"passed_time":11.53813236,"remaining_time":12.88119538},
{"learn":[0.6435809377],"iteration":189,"passed_time":11.61324248,"remaining_time":12.83568906},
{"learn":[0.643494513],"iteration":190,"passed_time":11.68108913,"remaining_time":12.78192476},
{"learn":[0.6434378886],"iteration":191,"passed_time":11.75589369,"remaining_time":12.7355515},
{"learn":[0.6433673085],"iteration":192,"passed_time":11.82043563,"remaining_time":12.67787656},
{"learn":[0.6433017408],"iteration":193,"passed_time":11.88665032,"remaining_time":12.62190704},
{"learn":[0.6432490705],"iteration":194,"passed_time":11.94940076,"remaining_time":12.56219055},
{"learn":[0.643187902],"iteration":195,"passed_time":12.00649379,"remaining_time":12.49655476},
{"learn":[0.6431464298],"iteration":196,"passed_time":12.07402797,"remaining_time":12.44176486},
{"learn":[0.6431053662],"iteration":197,"passed_time":12.14559788,"remaining_time":12.39096349},
{"learn":[0.6430593027],"iteration":198,"passed_time":12.20314134,"remaining_time":12.32578598},
{"learn":[0.6430136281],"iteration":199,"passed_time":12.26618001,"remaining_time":12.26618001},
{"learn":[0.6429617688],"iteration":200,"passed_time":12.33426001,"remaining_time":12.21153105},
{"learn":[0.6429153253],"iteration":201,"passed_time":12.38265955,"remaining_time":12.13745837},
{"learn":[0.6428630421],"iteration":202,"passed_time":12.44713558,"remaining_time":12.07923995},
{"learn":[0.6428086863],"iteration":203,"passed_time":12.51377966,"remaining_time":12.02304321},
{"learn":[0.6427615882],"iteration":204,"passed_time":12.57588363,"remaining_time":11.96242589},
{"learn":[0.6427399812],"iteration":205,"passed_time":12.61383951,"remaining_time":11.87905274},
{"learn":[0.6426961406],"iteration":206,"passed_time":12.68022694,"remaining_time":11.82262705},
{"learn":[0.6426482664],"iteration":207,"passed_time":12.736489,"remaining_time":11.75675908},
{"learn":[0.6425685787],"iteration":208,"passed_time":12.81376358,"remaining_time":11.71018585},
{"learn":[0.6425107172],"iteration":209,"passed_time":12.87551983,"remaining_time":11.64927985},
{"learn":[0.6424493518],"iteration":210,"passed_time":12.93435251,"remaining_time":11.58574703},
{"learn":[0.6424047501],"iteration":211,"passed_time":12.9886796,"remaining_time":11.51826304},
{"learn":[0.6423680676],"iteration":212,"passed_time":13.05528685,"remaining_time":11.46168376},
{"learn":[0.6422955205],"iteration":213,"passed_time":13.12575775,"remaining_time":11.40836889},
{"learn":[0.6422485271],"iteration":214,"passed_time":13.1850286,"remaining_time":11.34525717},
{"learn":[0.6422214686],"iteration":215,"passed_time":13.23702782,"remaining_time":11.27598666},
{"learn":[0.6421707579],"iteration":216,"passed_time":13.29799261,"remaining_time":11.21443616},
{"learn":[0.6421191432],"iteration":217,"passed_time":13.36343649,"remaining_time":11.15663046},
{"learn":[0.6420681318],"iteration":218,"passed_time":13.43112233,"remaining_time":11.10060795},
{"learn":[0.6420136008],"iteration":219,"passed_time":13.47552837,"remaining_time":11.02543231},
{"learn":[0.641937517],"iteration":220,"passed_time":13.54825908,"remaining_time":10.97347681},
{"learn":[0.6418828274],"iteration":221,"passed_time":13.6091865,"remaining_time":10.91187025},
{"learn":[0.6418152639],"iteration":222,"passed_time":13.67403787,"remaining_time":10.85338432},
{"learn":[0.6417787243],"iteration":223,"passed_time":13.73823465,"remaining_time":10.79432722},
{"learn":[0.6417466306],"iteration":224,"passed_time":13.8078808,"remaining_time":10.73946285},
{"learn":[0.641710849],"iteration":225,"passed_time":13.87909317,"remaining_time":10.6856735},
{"learn":[0.6416672176],"iteration":226,"passed_time":13.94974886,"remaining_time":10.6313064},
{"learn":[0.6416340659],"iteration":227,"passed_time":14.01591087,"remaining_time":10.57340645},
{"learn":[0.6415838545],"iteration":228,"passed_time":14.07071467,"remaining_time":10.50695287},
{"learn":[0.641539499],"iteration":229,"passed_time":14.12133553,"remaining_time":10.43750887},
{"learn":[0.6414844616],"iteration":230,"passed_time":14.19220729,"remaining_time":10.38304343},
{"learn":[0.6414343092],"iteration":231,"passed_time":14.26371336,"remaining_time":10.32889588},
{"learn":[0.641382696],"iteration":232,"passed_time":14.32324274,"remaining_time":10.26601518},
{"learn":[0.6413069422],"iteration":233,"passed_time":14.39216633,"remaining_time":10.2098274},
{"learn":[0.6412710986],"iteration":234,"passed_time":14.45690847,"remaining_time":10.15059531},
{"learn":[0.6412400768],"iteration":235,"passed_time":14.52310437,"remaining_time":10.09232677},
{"learn":[0.6412032072],"iteration":236,"passed_time":14.58972786,"remaining_time":10.03428541},
{"learn":[0.6411677276],"iteration":237,"passed_time":14.64698491,"remaining_time":9.969796449},
{"learn":[0.6411110594],"iteration":238,"passed_time":14.70896966,"remaining_time":9.908552785},
{"learn":[0.6410453385],"iteration":239,"passed_time":14.77342094,"remaining_time":9.848947295},
{"learn":[0.6410104143],"iteration":240,"passed_time":14.83521722,"remaining_time":9.787549952},
{"learn":[0.6409602316],"iteration":241,"passed_time":14.89994,"remaining_time":9.728059999},
{"learn":[0.6409200749],"iteration":242,"passed_time":14.9657805,"remaining_time":9.669249128},
{"learn":[0.6408958877],"iteration":243,"passed_time":15.0338647,"remaining_time":9.611815135},
{"learn":[0.6408757875],"iteration":244,"passed_time":15.09666371,"remaining_time":9.550950513},
{"learn":[0.6408380738],"iteration":245,"passed_time":15.16346469,"remaining_time":9.492575459},
{"learn":[0.6407991976],"iteration":246,"passed_time":15.22166577,"remaining_time":9.428805115},
{"learn":[0.6407750887],"iteration":247,"passed_time":15.3094187,"remaining_time":9.383192109},
{"learn":[0.6407355347],"iteration":248,"passed_time":15.36252081,"remaining_time":9.316227481},
{"learn":[0.6406651919],"iteration":249,"passed_time":15.42985728,"remaining_time":9.257914368},
{"learn":[0.6405935436],"iteration":250,"passed_time":15.50017072,"remaining_time":9.20129656},
{"learn":[0.6404994587],"iteration":251,"passed_time":15.5641591,"remaining_time":9.140855343},
{"learn":[0.6404690735],"iteration":252,"passed_time":15.61554116,"remaining_time":9.073061463},
{"learn":[0.6404031716],"iteration":253,"passed_time":15.66267257,"remaining_time":9.002953522},
{"learn":[0.6403435167],"iteration":254,"passed_time":15.72567397,"remaining_time":8.942049905},
{"learn":[0.6403079304],"iteration":255,"passed_time":15.78524295,"remaining_time":8.879199159},
{"learn":[0.6402722593],"iteration":256,"passed_time":15.84345073,"remaining_time":8.815616554},
{"learn":[0.6402010925],"iteration":257,"passed_time":15.90192424,"remaining_time":8.75222187},
{"learn":[0.6401692596],"iteration":258,"passed_time":15.96131135,"remaining_time":8.689362551},
{"learn":[0.6401241152],"iteration":259,"passed_time":16.02863787,"remaining_time":8.630805009},
{"learn":[0.6400831567],"iteration":260,"passed_time":16.08961212,"remaining_time":8.568797258},
{"learn":[0.6400407895],"iteration":261,"passed_time":16.16295428,"remaining_time":8.513311794},
{"learn":[0.6399611037],"iteration":262,"passed_time":16.23140507,"remaining_time":8.455142567},
{"learn":[0.6398682978],"iteration":263,"passed_time":16.29050366,"remaining_time":8.392077644},
{"learn":[0.6398057152],"iteration":264,"passed_time":16.34718376,"remaining_time":8.327810597},
{"learn":[0.6397871182],"iteration":265,"passed_time":16.41124616,"remaining_time":8.267319493},
{"learn":[0.6397354846],"iteration":266,"passed_time":16.47395274,"remaining_time":8.206126273},
{"learn":[0.6396873617],"iteration":267,"passed_time":16.53133385,"remaining_time":8.142298763},
{"learn":[0.6396298363],"iteration":268,"passed_time":16.59148992,"remaining_time":8.079870558},
{"learn":[0.6395877442],"iteration":269,"passed_time":16.65632089,"remaining_time":8.01971006},
{"learn":[0.6395344677],"iteration":270,"passed_time":16.7275659,"remaining_time":7.962568269},
{"learn":[0.639447509],"iteration":271,"passed_time":16.79351638,"remaining_time":7.902831239},
{"learn":[0.6393868888],"iteration":272,"passed_time":16.85030185,"remaining_time":7.838785109},
{"learn":[0.6393598441],"iteration":273,"passed_time":16.91606699,"remaining_time":7.778921318},
{"learn":[0.6393104242],"iteration":274,"passed_time":16.979227,"remaining_time":7.717830456},
{"learn":[0.6392567108],"iteration":275,"passed_time":17.03182401,"remaining_time":7.651978902},
{"learn":[0.6391962515],"iteration":276,"passed_time":17.09815024,"remaining_time":7.592319422},
{"learn":[0.639139372],"iteration":277,"passed_time":17.15359304,"remaining_time":7.527835795},
{"learn":[0.63907526],"iteration":278,"passed_time":17.22516662,"remaining_time":7.470412762},
{"learn":[0.6390068467],"iteration":279,"passed_time":17.28120035,"remaining_time":7.406228724},
{"learn":[0.6389742891],"iteration":280,"passed_time":17.33614802,"remaining_time":7.341642754},
{"learn":[0.6389410698],"iteration":281,"passed_time":17.40717366,"remaining_time":7.283852808},
{"learn":[0.6389056893],"iteration":282,"passed_time":17.4565705,"remaining_time":7.21702738},
{"learn":[0.6388506876],"iteration":283,"passed_time":17.51793845,"remaining_time":7.155214295},
{"learn":[0.6387903156],"iteration":284,"passed_time":17.57671453,"remaining_time":7.092358493},
{"learn":[0.63875183],"iteration":285,"passed_time":17.63246971,"remaining_time":7.028327089},
{"learn":[0.6387213477],"iteration":286,"passed_time":17.69324882,"remaining_time":6.966331418},
{"learn":[0.6386777646],"iteration":287,"passed_time":17.74097322,"remaining_time":6.899267365},
{"learn":[0.6386378128],"iteration":288,"passed_time":17.8016661,"remaining_time":6.837318122},
{"learn":[0.6385839337],"iteration":289,"passed_time":17.85912688,"remaining_time":6.774151576},
{"learn":[0.6385642132],"iteration":290,"passed_time":17.93108465,"remaining_time":6.716454388},
{"learn":[0.6385125209],"iteration":291,"passed_time":18.0047783,"remaining_time":6.659301564},
{"learn":[0.6384714735],"iteration":292,"passed_time":18.06399653,"remaining_time":6.596749587},
{"learn":[0.6384228973],"iteration":293,"passed_time":18.13187979,"remaining_time":6.537344413},
{"learn":[0.6383904638],"iteration":294,"passed_time":18.18589249,"remaining_time":6.472944786},
{"learn":[0.6383494753],"iteration":295,"passed_time":18.24255486,"remaining_time":6.409546301},
{"learn":[0.6383288876],"iteration":296,"passed_time":18.3156353,"remaining_time":6.351886991},
{"learn":[0.6382879744],"iteration":297,"passed_time":18.38918163,"remaining_time":6.294283646},
{"learn":[0.6382488456],"iteration":298,"passed_time":18.44285884,"remaining_time":6.229862016},
{"learn":[0.638159366],"iteration":299,"passed_time":18.516263,"remaining_time":6.172087667},
{"learn":[0.6381159569],"iteration":300,"passed_time":18.5720611,"remaining_time":6.108418766},
{"learn":[0.6380985075],"iteration":301,"passed_time":18.6388632,"remaining_time":6.048372826},
{"learn":[0.6380610349],"iteration":302,"passed_time":18.70617308,"remaining_time":5.988444847},
{"learn":[0.6380415235],"iteration":303,"passed_time":18.76562941,"remaining_time":5.925988234},
{"learn":[0.6380197935],"iteration":304,"passed_time":18.81911164,"remaining_time":5.86169051},
{"learn":[0.6379846702],"iteration":305,"passed_time":18.88881734,"remaining_time":5.802447157},
{"learn":[0.6379533818],"iteration":306,"passed_time":18.95882089,"remaining_time":5.743225873},
{"learn":[0.6379271818],"iteration":307,"passed_time":19.0293027,"remaining_time":5.684077429},
{"learn":[0.6378963379],"iteration":308,"passed_time":19.08302402,"remaining_time":5.619919694},
{"learn":[0.6378384645],"iteration":309,"passed_time":19.15289128,"remaining_time":5.560516825},
{"learn":[0.637808819],"iteration":310,"passed_time":19.21417706,"remaining_time":5.498590862},
{"learn":[0.6377734241],"iteration":311,"passed_time":19.27985675,"remaining_time":5.437908314},
{"learn":[0.6377501908],"iteration":312,"passed_time":19.33358315,"remaining_time":5.373871356},
{"learn":[0.6377024041],"iteration":313,"passed_time":19.39915285,"remaining_time":5.313143773},
{"learn":[0.6376654055],"iteration":314,"passed_time":19.45746162,"remaining_time":5.250426153},
{"learn":[0.6376171108],"iteration":315,"passed_time":19.50268211,"remaining_time":5.184257269},
{"learn":[0.6375900775],"iteration":316,"passed_time":19.56368326,"remaining_time":5.1223524},
{"learn":[0.6375710799],"iteration":317,"passed_time":19.63562173,"remaining_time":5.063273528},
{"learn":[0.6375387986],"iteration":318,"passed_time":19.70691359,"remaining_time":5.003949845},
{"learn":[0.6375063387],"iteration":319,"passed_time":19.77454964,"remaining_time":4.943637409},
{"learn":[0.6374883867],"iteration":320,"passed_time":19.84353153,"remaining_time":4.883610563},
{"learn":[0.6374554333],"iteration":321,"passed_time":19.90732455,"remaining_time":4.822271165},
{"learn":[0.6374125751],"iteration":322,"passed_time":19.97304783,"remaining_time":4.761376727},
{"learn":[0.6373898069],"iteration":323,"passed_time":20.04191259,"remaining_time":4.701189372},
{"learn":[0.6373468849],"iteration":324,"passed_time":20.1070681,"remaining_time":4.640092638},
{"learn":[0.6373181753],"iteration":325,"passed_time":20.16476557,"remaining_time":4.577278074},
{"learn":[0.637277624],"iteration":326,"passed_time":20.22397844,"remaining_time":4.514833107},
{"learn":[0.6372604899],"iteration":327,"passed_time":20.28700408,"remaining_time":4.453244798},
{"learn":[0.6372353162],"iteration":328,"passed_time":20.35141278,"remaining_time":4.391946222},
{"learn":[0.6372084432],"iteration":329,"passed_time":20.41520535,"remaining_time":4.330498105},
{"learn":[0.6371604671],"iteration":330,"passed_time":20.472233,"remaining_time":4.267625611},
{"learn":[0.6371191379],"iteration":331,"passed_time":20.53763888,"remaining_time":4.206504348},
{"learn":[0.6370948645],"iteration":332,"passed_time":20.60568846,"remaining_time":4.145889269},
{"learn":[0.637073319],"iteration":333,"passed_time":20.68304914,"remaining_time":4.08706959},
{"learn":[0.6369914944],"iteration":334,"passed_time":20.7526087,"remaining_time":4.026625569},
{"learn":[0.63694237],"iteration":335,"passed_time":20.81753092,"remaining_time":3.965243984},
{"learn":[0.6369065402],"iteration":336,"passed_time":20.87997382,"remaining_time":3.903377896},
{"learn":[0.6368712815],"iteration":337,"passed_time":20.95378263,"remaining_time":3.843593264},
{"learn":[0.6368254302],"iteration":338,"passed_time":21.02430067,"remaining_time":3.783133748},
{"learn":[0.6368043357],"iteration":339,"passed_time":21.08631665,"remaining_time":3.721114702},
{"learn":[0.6367681816],"iteration":340,"passed_time":21.15536029,"remaining_time":3.660311604},
{"learn":[0.6367341506],"iteration":341,"passed_time":21.23174621,"remaining_time":3.600705497},
{"learn":[0.636709287],"iteration":342,"passed_time":21.30165273,"remaining_time":3.539924798},
{"learn":[0.6366731499],"iteration":343,"passed_time":21.36586305,"remaining_time":3.478163752},
{"learn":[0.636669693],"iteration":344,"passed_time":21.38337003,"remaining_time":3.408943048},
{"learn":[0.636635711],"iteration":345,"passed_time":21.44331374,"remaining_time":3.346644341},
{"learn":[0.636604894],"iteration":346,"passed_time":21.51525614,"remaining_time":3.28619186},
{"learn":[0.6365717718],"iteration":347,"passed_time":21.56982825,"remaining_time":3.223077784},
{"learn":[0.6365187308],"iteration":348,"passed_time":21.6299816,"remaining_time":3.160828257},
{"learn":[0.636507112],"iteration":349,"passed_time":21.69116951,"remaining_time":3.098738501},
{"learn":[0.6364883543],"iteration":350,"passed_time":21.74391219,"remaining_time":3.035474922},
{"learn":[0.6364601612],"iteration":351,"passed_time":21.81068709,"remaining_time":2.974184603},
{"learn":[0.6364371535],"iteration":352,"passed_time":21.87717501,"remaining_time":2.912825002},
{"learn":[0.6364187968],"iteration":353,"passed_time":21.95285805,"remaining_time":2.852631272},
{"learn":[0.6363829875],"iteration":354,"passed_time":22.02068882,"remaining_time":2.791354921},
{"learn":[0.636360554],"iteration":355,"passed_time":22.07444311,"remaining_time":2.728301958},
{"learn":[0.6363254289],"iteration":356,"passed_time":22.12756517,"remaining_time":2.665224936},
{"learn":[0.6362983484],"iteration":357,"passed_time":22.17912928,"remaining_time":2.602020754},
{"learn":[0.6362807038],"iteration":358,"passed_time":22.24143963,"remaining_time":2.540108705},
{"learn":[0.6362556087],"iteration":359,"passed_time":22.30425684,"remaining_time":2.47825076},
{"learn":[0.6362256886],"iteration":360,"passed_time":22.37907189,"remaining_time":2.417683667},
{"learn":[0.6361987407],"iteration":361,"passed_time":22.44780137,"remaining_time":2.356399039},
{"learn":[0.6361785105],"iteration":362,"passed_time":22.50419299,"remaining_time":2.293815815},
{"learn":[0.6361478693],"iteration":363,"passed_time":22.56044614,"remaining_time":2.231252915},
{"learn":[0.6361207571],"iteration":364,"passed_time":22.6115065,"remaining_time":2.168226651},
{"learn":[0.6361038879],"iteration":365,"passed_time":22.68311413,"remaining_time":2.107174537},
{"learn":[0.6360675847],"iteration":366,"passed_time":22.74710513,"remaining_time":2.045380026},
{"learn":[0.6360231839],"iteration":367,"passed_time":22.82696653,"remaining_time":1.984953612},
{"learn":[0.6359841456],"iteration":368,"passed_time":22.89356728,"remaining_time":1.92330782},
{"learn":[0.6359626636],"iteration":369,"passed_time":22.95720228,"remaining_time":1.861394779},
{"learn":[0.6359482938],"iteration":370,"passed_time":23.00606615,"remaining_time":1.798317839},
{"learn":[0.6359272239],"iteration":371,"passed_time":23.07677034,"remaining_time":1.736961208},
{"learn":[0.6359104788],"iteration":372,"passed_time":23.14541453,"remaining_time":1.675405341},
{"learn":[0.6358770355],"iteration":373,"passed_time":23.2062372,"remaining_time":1.613267827},
{"learn":[0.6358513479],"iteration":374,"passed_time":23.26347599,"remaining_time":1.550898399},
{"learn":[0.635828082],"iteration":375,"passed_time":23.32345715,"remaining_time":1.488731308},
{"learn":[0.6357993311],"iteration":376,"passed_time":23.39190951,"remaining_time":1.427092622},
{"learn":[0.6357703689],"iteration":377,"passed_time":23.4635773,"remaining_time":1.365605028},
{"learn":[0.635755846],"iteration":378,"passed_time":23.52257821,"remaining_time":1.303361853},
{"learn":[0.6357313122],"iteration":379,"passed_time":23.57343761,"remaining_time":1.240707243},
{"learn":[0.6357103526],"iteration":380,"passed_time":23.64240129,"remaining_time":1.179017387},
{"learn":[0.6356905042],"iteration":381,"passed_time":23.71298114,"remaining_time":1.117365604},
{"learn":[0.6356766382],"iteration":382,"passed_time":23.77669071,"remaining_time":1.055362251},
{"learn":[0.6356640013],"iteration":383,"passed_time":23.83112923,"remaining_time":0.992963718},
{"learn":[0.6356465923],"iteration":384,"passed_time":23.90283916,"remaining_time":0.931279448},
{"learn":[0.6356172848],"iteration":385,"passed_time":23.97181955,"remaining_time":0.8694442325},
{"learn":[0.6355924994],"iteration":386,"passed_time":24.03772749,"remaining_time":0.807468882},
{"learn":[0.6355741977],"iteration":387,"passed_time":24.08964608,"remaining_time":0.7450406003},
{"learn":[0.635551977],"iteration":388,"passed_time":24.145575,"remaining_time":0.6827797559},
{"learn":[0.6355022087],"iteration":389,"passed_time":24.2101225,"remaining_time":0.6207723719},
{"learn":[0.6354777042],"iteration":390,"passed_time":24.28217047,"remaining_time":0.55892464},
{"learn":[0.6354659647],"iteration":391,"passed_time":24.34969878,"remaining_time":0.4969326281},
{"learn":[0.6354197953],"iteration":392,"passed_time":24.41457068,"remaining_time":0.4348651265},
{"learn":[0.6354005648],"iteration":393,"passed_time":24.48799429,"remaining_time":0.3729136187},
{"learn":[0.6353637092],"iteration":394,"passed_time":24.55696719,"remaining_time":0.310847686},
{"learn":[0.6353623951],"iteration":395,"passed_time":24.58568976,"remaining_time":0.2483403006},
{"learn":[0.6353305801],"iteration":396,"passed_time":24.66203931,"remaining_time":0.1863630175},
{"learn":[0.6352989237],"iteration":397,"passed_time":24.7310312,"remaining_time":0.1242765387},
{"learn":[0.6352737634],"iteration":398,"passed_time":24.80630288,"remaining_time":0.06217118517},
{"learn":[0.6352533187],"iteration":399,"passed_time":24.86863643,"remaining_time":0}
]}